look4it/__init__.py
look4it/__main__.py
look4it/cli.py
look4it/search_tool.py
look4it-0.1.0.dist-info/licenses/LICENSE
look4it-0.1.0.dist-info/METADATA
look4it-0.1.0.dist-info/WHEEL
look4it-0.1.0.dist-info/entry_points.txt
look4it-0.1.0.dist-info/top_level.txt
look4it-0.1.0.dist-info/RECORD
