Metadata-Version: 2.4
Name: look4it
Version: 0.1.0
Summary: A simple web searching tool similar to Tavily
Author: Look4It Contributors
License-Expression: MIT
Project-URL: Homepage, https://github.com/yourusername/look4it
Project-URL: Documentation, https://github.com/yourusername/look4it#readme
Project-URL: Repository, https://github.com/yourusername/look4it
Project-URL: Issues, https://github.com/yourusername/look4it/issues
Keywords: search,web,scraping,duckduckgo,content-extraction
Classifier: Development Status :: 3 - Alpha
Classifier: Intended Audience :: Developers
Classifier: Programming Language :: Python :: 3
Classifier: Programming Language :: Python :: 3.10
Classifier: Programming Language :: Python :: 3.11
Classifier: Programming Language :: Python :: 3.12
Classifier: Topic :: Software Development :: Libraries :: Python Modules
Classifier: Topic :: Internet :: WWW/HTTP :: Indexing/Search
Requires-Python: >=3.10
License-File: LICENSE
Requires-Dist: requests>=2.31.0
Requires-Dist: beautifulsoup4>=4.12.0
Requires-Dist: ddgs>=9.0.0
Requires-Dist: lxml>=5.0.0
Provides-Extra: test
Requires-Dist: pytest>=9.0.0; extra == "test"
Requires-Dist: pytest-cov>=7.0.0; extra == "test"
Requires-Dist: pytest-mock>=3.15.0; extra == "test"
Dynamic: license-file
